willj/__init__.py
willj/will.py
willj-0.1.2.dist-info/LICENSE
willj-0.1.2.dist-info/METADATA
willj-0.1.2.dist-info/WHEEL
willj-0.1.2.dist-info/top_level.txt
willj-0.1.2.dist-info/RECORD
