Metadata-Version: 2.2
Name: willj
Version: 0.1.2
Summary: A personal package I can use to test on pypi and github actions
Requires-Python: >=3.12
License-File: LICENSE
